{
  "version": 4,
  "configurePresets": [
    {
      "name": "vs2019",
      "displayName": "游댯 Visual Studio 2019 (x64)",
      "description": "Genera soluci칩n .sln para Visual Studio 2019 (x64).",
      "generator": "Visual Studio 16 2019",
      "binaryDir": "${sourceDir}/build/vs2019",
      "architecture": "x64",
      "cacheVariables": {
        "CMAKE_CXX_FLAGS": "/W3 /WX /EHsc /ZI",
        "CMAKE_CXX_FLAGS_DEBUG": "/W3 /WX /EHsc /ZI /Od"
      }
    },
    {
      "name": "vs2022",
      "displayName": "游릭 Visual Studio 2022 (x64)",
      "description": "Genera soluci칩n .sln para Visual Studio 2022 (x64).",
      "generator": "Visual Studio 17 2022",
      "binaryDir": "${sourceDir}/build/vs2022",
      "architecture": "x64",
      "cacheVariables": {
        "CMAKE_CXX_FLAGS": "/W3 /WX /EHsc /ZI",
        "CMAKE_CXX_FLAGS_DEBUG": "/W3 /WX /EHsc /ZI /Od"
      }
    },
    {
      "name": "vs2026",
      "displayName": "游릮 Visual Studio 2026 (x64)",
      "description": "Genera soluci칩n .sln para Visual Studio 2026 (x64).",
      "generator": "Visual Studio 18 2026",
      "binaryDir": "${sourceDir}/build/vs2026",
      "architecture": "x64",
      "cacheVariables": {
        "CMAKE_CXX_FLAGS": "/W3 /WX /EHsc /ZI",
        "CMAKE_CXX_FLAGS_DEBUG": "/W3 /WX /EHsc /ZI /Od"
      }
    },
    {
      "name": "ninja-windows-mingw64",
      "displayName": "游리 Ninja Windows (MinGW-w64 classic)",
      "description": "Build en Windows con MinGW-w64.",
      "generator": "Ninja",
      "binaryDir": "${sourceDir}/build/ninja-windows-mingw64",
      "toolchainFile": "toolchains/mingw-mingw64.cmake",
      "cacheVariables": {
        "CMAKE_CXX_FLAGS": "-Wall -Wextra -Wpedantic -Werror"
      },
      "condition": {
        "type": "equals",
        "lhs": "${hostSystemName}",
        "rhs": "Windows"
      }
    }
  ],
  "buildPresets": [
    {
      "name": "windows-mingw64-debug",
      "displayName": "Mingw64 Debug",
      "configurePreset": "ninja-windows-mingw64",
      "configuration": "Debug"
    },
    {
      "name": "windows-mingw64-release",
      "displayName": "Mingw64 Release",
      "configurePreset": "ninja-windows-mingw64",
      "configuration": "Release"
    },
    {
      "name": "vs2019-release",
      "displayName": "游 VS2019 Release (x64)",
      "configurePreset": "vs2019",
      "configuration": "Release"
    },
    {
      "name": "vs2019-debug",
      "displayName": "游 VS2019 Debug (x64)",
      "configurePreset": "vs2019",
      "configuration": "Debug"
    },
    {
      "name": "vs2019-relwithdebinfo",
      "displayName": "游댌 VS2019 RelWithDebInfo (x64)",
      "configurePreset": "vs2019",
      "configuration": "RelWithDebInfo"
    },
    {
      "name": "vs2019-minsizerel",
      "displayName": "游닍 VS2019 MinSizeRel (x64)",
      "configurePreset": "vs2019",
      "configuration": "MinSizeRel"
    },
    {
      "name": "vs2022-release",
      "displayName": "游 VS2022 Release (x64)",
      "configurePreset": "vs2022",
      "configuration": "Release"
    },
    {
      "name": "vs2022-debug",
      "displayName": "游 VS2022 Debug (x64)",
      "configurePreset": "vs2022",
      "configuration": "Debug"
    },
    {
      "name": "vs2022-relwithdebinfo",
      "displayName": "游댌 VS2022 RelWithDebInfo (x64)",
      "configurePreset": "vs2022",
      "configuration": "RelWithDebInfo"
    },
    {
      "name": "vs2022-minsizerel",
      "displayName": "游닍 VS2022 MinSizeRel (x64)",
      "configurePreset": "vs2022",
      "configuration": "MinSizeRel"
    },
    {
      "name": "vs2026-release",
      "displayName": "游 VS2026 Release (x64)",
      "configurePreset": "vs2026",
      "configuration": "Release"
    },
    {
      "name": "vs2026-debug",
      "displayName": "游 VS2026 Debug (x64)",
      "configurePreset": "vs2026",
      "configuration": "Debug"
    },
    {
      "name": "vs2026-relwithdebinfo",
      "displayName": "游댌 VS2026 RelWithDebInfo (x64)",
      "configurePreset": "vs2026",
      "configuration": "RelWithDebInfo"
    },
    {
      "name": "vs2026-minsizerel",
      "displayName": "游닍 VS2026 MinSizeRel (x64)",
      "configurePreset": "vs2026",
      "configuration": "MinSizeRel"
    }
  ]
}
